ttauto_crawler/__init__.py
ttauto_crawler/auto_crawler.py
ttauto_crawler/binary.py
ttauto_crawler/downloader.py
ttauto_crawler/main.py
ttauto_crawler/mecord_downloader.py
ttauto_crawler/processing.py
ttauto_crawler/task.py
ttauto_crawler/ttsUtils.py
ttauto_crawler/txt2proj.py
ttauto_crawler/uploading.py
ttauto_crawler/utils.py
ttauto_crawler/video_merge.py
ttauto_crawler/video_random_cutter.py
ttauto_crawler/ytdlp_downloader.py
ttauto_crawler/bin/__init__.py
ttauto_crawler/bin/print_md5.py
p_ttauto_crawler-0.1.40.dist-info/LICENSE
p_ttauto_crawler-0.1.40.dist-info/METADATA
p_ttauto_crawler-0.1.40.dist-info/WHEEL
p_ttauto_crawler-0.1.40.dist-info/entry_points.txt
p_ttauto_crawler-0.1.40.dist-info/top_level.txt
p_ttauto_crawler-0.1.40.dist-info/RECORD
