Metadata-Version: 2.1
Name: p-ttauto-crawler
Version: 0.1.40
Summary: template tools
Author: pengjun
Author-email: mr_lonely@foxmail.com
Classifier: Programming Language :: Python :: 3
Classifier: License :: OSI Approved :: MIT License
Classifier: Operating System :: OS Independent
Requires-Python: >=3.7
License-File: LICENSE
Requires-Dist: requests
Requires-Dist: oss2
Requires-Dist: Image
Requires-Dist: Pillow
Requires-Dist: p-template-generator (>=0.1.71)
Requires-Dist: fake-useragent
Requires-Dist: mutagen
Requires-Dist: yt-dlp (==2023.3.4)
Requires-Dist: moviepy
Requires-Dist: urlparser
